<?xml version="1.0" encoding="utf-8" ?><dwsync><file name="background-wide-wallpaper-1920x1080-005.jpg" server="scottbrabazon.com" local="3521289692" remote="12127184252" /><file name="linkedin.png" server="scottbrabazon.com" local="3521289956" remote="12127184252" /><file name="wd40cans1.jpg" server="scottbrabazon.com" local="3521289703" remote="12126827492" /><file name="wd40cans2.jpg" server="scottbrabazon.com" local="3521289703" remote="12126827492" /><file name="aflemail.jpg" server="scottbrabazon.com" local="3521289690" remote="12127184252" /><file name="spacer.gif" server="scottbrabazon.com" local="3521289702" remote="12126827432" /><file name="arrow.gif" server="scottbrabazon.com" local="3517735234" remote="12126827372" /><file name="bikeandgo.jpg" server="scottbrabazon.com" local="3521289693" remote="12127184252" /><file name="joneshomesemail.jpg" server="scottbrabazon.com" local="3521289697" remote="12127184252" /><file name="argos_ss2012_009.jpg" server="scottbrabazon.com" local="3521289690" remote="12126827372" /><file name="argos_ss2012_013.jpg" server="scottbrabazon.com" local="3521289691" remote="12126827372" /><file name="argos_ss2012_031.jpg" server="scottbrabazon.com" local="3521289691" remote="12126827372" /><file name="argos_ss2012_034.jpg" server="scottbrabazon.com" local="3521289691" remote="12126827372" /><file name="argos_ss2012_036.jpg" server="scottbrabazon.com" local="3521289691" remote="12126827372" /><file name="argos_ss2012_039.jpg" server="scottbrabazon.com" local="3521289692" remote="12126827372" /><file name="argos_ss2012_044.jpg" server="scottbrabazon.com" local="3521289692" remote="12126827372" /><file name="argos_ss2012_051.jpg" server="scottbrabazon.com" local="3521289692" remote="12126827372" /><file name="argos_ss2012_thumbnail.png" server="scottbrabazon.com" local="3521290020" remote="12126827372" /><file name="chelsea4.jpg" server="scottbrabazon.com" local="3521289693" remote="12126827372" /><file name="chelsea5.jpg" server="scottbrabazon.com" local="3521289693" remote="12126827372" /><file name="chelsea7.jpg" server="scottbrabazon.com" local="3521289693" remote="12126827372" /><file name="chelsea8.jpg" server="scottbrabazon.com" local="3521289693" remote="12126827372" /><file name="chelsea_thumbnail.png" server="scottbrabazon.com" local="3521290003" remote="12126827372" /><file name="close.png" server="scottbrabazon.com" local="3521289997" remote="12127183172" /><file name="guitar_thumbnail.png" server="scottbrabazon.com" local="3521289981" remote="12126827372" /><file name="loading.gif" server="scottbrabazon.com" local="3479013910" remote="12127183172" /><file name="mancitystore_1.jpg" server="scottbrabazon.com" local="3521289698" remote="12126827372" /><file name="mancitystore_10.jpg" server="scottbrabazon.com" local="3521289698" remote="12126827372" /><file name="mancitystore_11.jpg" server="scottbrabazon.com" local="3521289698" remote="12126827372" /><file name="mancitystore_12.jpg" server="scottbrabazon.com" local="3521289698" remote="12126827372" /><file name="mancitystore_13.jpg" server="scottbrabazon.com" local="3521289699" remote="12126827372" /><file name="mancitystore_14.jpg" server="scottbrabazon.com" local="3521289699" remote="12126827432" /><file name="mancitystore_15.jpg" server="scottbrabazon.com" local="3521289699" remote="12126827432" /><file name="mancitystore_16.jpg" server="scottbrabazon.com" local="3521289699" remote="12126827432" /><file name="mancitystore_17.jpg" server="scottbrabazon.com" local="3521289699" remote="12126827432" /><file name="mancitystore_18.jpg" server="scottbrabazon.com" local="3521289699" remote="12126827432" /><file name="mancitystore_19.jpg" server="scottbrabazon.com" local="3521289699" remote="12126827432" /><file name="mancitystore_2.jpg" server="scottbrabazon.com" local="3521289698" remote="12126827432" /><file name="mancitystore_20.jpg" server="scottbrabazon.com" local="3521289699" remote="12126827432" /><file name="mancitystore_21.jpg" server="scottbrabazon.com" local="3521289699" remote="12126827432" /><file name="mancitystore_22.jpg" server="scottbrabazon.com" local="3521289699" remote="12126827432" /><file name="mancitystore_23.jpg" server="scottbrabazon.com" local="3521289699" remote="12126827432" /><file name="mancitystore_24.jpg" server="scottbrabazon.com" local="3521289699" remote="12126827432" /><file name="mancitystore_25.jpg" server="scottbrabazon.com" local="3521289699" remote="12126827432" /><file name="mancitystore_26.jpg" server="scottbrabazon.com" local="3521289699" remote="12126827432" /><file name="mancitystore_27.jpg" server="scottbrabazon.com" local="3521289699" remote="12126827432" /><file name="mancitystore_28.jpg" server="scottbrabazon.com" local="3521289700" remote="12126827432" /><file name="mancitystore_29.jpg" server="scottbrabazon.com" local="3521289700" remote="12126827432" /><file name="mancitystore_3.jpg" server="scottbrabazon.com" local="3521289698" remote="12126827432" /><file name="mancitystore_4.jpg" server="scottbrabazon.com" local="3521289698" remote="12126827432" /><file name="mancitystore_5.jpg" server="scottbrabazon.com" local="3521289698" remote="12126827432" /><file name="mancitystore_6.jpg" server="scottbrabazon.com" local="3521289698" remote="12126827432" /><file name="mancitystore_7.jpg" server="scottbrabazon.com" local="3521289698" remote="12126827432" /><file name="mancitystore_8.jpg" server="scottbrabazon.com" local="3521289698" remote="12126827432" /><file name="mancitystore_9.jpg" server="scottbrabazon.com" local="3521289698" remote="12126827432" /><file name="mancitystore_thumbnail.png" server="scottbrabazon.com" local="3521289950" remote="12126827432" /><file name="mcfc_002_003_intro.jpg" server="scottbrabazon.com" local="3521289700" remote="12126827432" /><file name="mcfc_004_005_intro_2.jpg" server="scottbrabazon.com" local="3521289700" remote="12126827432" /><file name="mcfc_008_009_home_kit.jpg" server="scottbrabazon.com" local="3521289700" remote="12126827432" /><file name="mcfc_014_015_personalisation.jpg" server="scottbrabazon.com" local="3521289700" remote="12126827432" /><file name="mcfc_024_025_my_first_game.jpg" server="scottbrabazon.com" local="3521289700" remote="12126827432" /><file name="mcfc_026_027_retro.jpg" server="scottbrabazon.com" local="3521289700" remote="12126827432" /><file name="mcfc_034_035_essentials.jpg" server="scottbrabazon.com" local="3521289700" remote="12126827432" /><file name="mcfc_038_039_essentials_2for20.jpg" server="scottbrabazon.com" local="3521289700" remote="12126827432" /><file name="mcfc_040_041_essentials_2for15.jpg" server="scottbrabazon.com" local="3521289700" remote="12126827432" /><file name="mcfc_046_047_essentials_womens_2for20.jpg" server="scottbrabazon.com" local="3521289701" remote="12126827432" /><file name="mcfc_050_051_competition.jpg" server="scottbrabazon.com" local="3521289701" remote="12126827432" /><file name="mcfc_052_053_accessories.jpg" server="scottbrabazon.com" local="3521289701" remote="12126827432" /><file name="mcfc_058_059_keyrings_badges.jpg" server="scottbrabazon.com" local="3521289701" remote="12126827432" /><file name="mcfc_062_063_soft_toys_stationery.jpg" server="scottbrabazon.com" local="3521289701" remote="12126827432" /><file name="mcfc_068_069_christmas_soft_toys.jpg" server="scottbrabazon.com" local="3521289701" remote="12126827432" /><file name="mcfc_072_073_mugs_retro_gifts.jpg" server="scottbrabazon.com" local="3521289701" remote="12126827432" /><file name="mcfc_084_001_front_back.jpg" server="scottbrabazon.com" local="3521289701" remote="12126827432" /><file name="mcfc_thumbnail.png" server="scottbrabazon.com" local="3521289944" remote="12126827432" /><file name="mufc2011.jpg" server="scottbrabazon.com" local="3521289701" remote="12126827432" /><file name="mufc201110.jpg" server="scottbrabazon.com" local="3521289702" remote="12126827432" /><file name="mufc201115.jpg" server="scottbrabazon.com" local="3521289702" remote="12126827432" /><file name="mufc201117.jpg" server="scottbrabazon.com" local="3521289702" remote="12126827432" /><file name="mufc20112.jpg" server="scottbrabazon.com" local="3521289701" remote="12126827432" /><file name="mufc201120.jpg" server="scottbrabazon.com" local="3521289702" remote="12126827432" /><file name="mufc201121.jpg" server="scottbrabazon.com" local="3521289702" remote="12126827432" /><file name="mufc20113.jpg" server="scottbrabazon.com" local="3521289701" remote="12126827432" /><file name="mufc20114.jpg" server="scottbrabazon.com" local="3521289701" remote="12126827432" /><file name="mufc201145.jpg" server="scottbrabazon.com" local="3521289702" remote="12126827432" /><file name="mufc20115.jpg" server="scottbrabazon.com" local="3521289701" remote="12126827432" /><file name="mufc20116.jpg" server="scottbrabazon.com" local="3521289702" remote="12126827432" /><file name="mufc20117.jpg" server="scottbrabazon.com" local="3521289702" remote="12126827432" /><file name="mufc20118.jpg" server="scottbrabazon.com" local="3521289702" remote="12126827432" /><file name="mufc2011_thumbnail.png" server="scottbrabazon.com" local="3521289938" remote="12126827432" /><file name="next.png" server="scottbrabazon.com" local="3521289932" remote="12127183172" /><file name="prev.png" server="scottbrabazon.com" local="3521289926" remote="12127183172" /><file name="wd40cans_thumbnail.png" server="scottbrabazon.com" local="3521289875" remote="12126827492" /><file name="world-cup-201010.jpg" server="scottbrabazon.com" local="3521289703" remote="12126827492" /><file name="world-cup-201011.jpg" server="scottbrabazon.com" local="3521289703" remote="12126827492" /><file name="world-cup-201012.jpg" server="scottbrabazon.com" local="3521289703" remote="12126827492" /><file name="world-cup-201013.jpg" server="scottbrabazon.com" local="3521289703" remote="12126827492" /><file name="world-cup-201014.jpg" server="scottbrabazon.com" local="3521289703" remote="12126827492" /><file name="world-cup-201015.jpg" server="scottbrabazon.com" local="3521289704" remote="12126827492" /><file name="world-cup-201016.jpg" server="scottbrabazon.com" local="3521289703" remote="12126827492" /><file name="world-cup-201017.jpg" server="scottbrabazon.com" local="3521289704" remote="12126827492" /><file name="world-cup-201018.jpg" server="scottbrabazon.com" local="3521289704" remote="12126827492" /><file name="world-cup-201019.jpg" server="scottbrabazon.com" local="3521289704" remote="12126827492" /><file name="world-cup-201020.jpg" server="scottbrabazon.com" local="3521289704" remote="12126827492" /><file name="world-cup-201021.jpg" server="scottbrabazon.com" local="3521289704" remote="12126827492" /><file name="world-cup-201022.jpg" server="scottbrabazon.com" local="3521289704" remote="12126827492" /><file name="world-cup-201023.jpg" server="scottbrabazon.com" local="3521289704" remote="12126827492" /><file name="world-cup-201024.jpg" server="scottbrabazon.com" local="3521289704" remote="12126827492" /><file name="world-cup-201025.jpg" server="scottbrabazon.com" local="3521289704" remote="12126827492" /><file name="world-cup-201026.jpg" server="scottbrabazon.com" local="3521289704" remote="12126827492" /><file name="world-cup-201027.jpg" server="scottbrabazon.com" local="3521289704" remote="12126827492" /><file name="world-cup-201028.jpg" server="scottbrabazon.com" local="3521289704" remote="12126827492" /><file name="world-cup-201029.jpg" server="scottbrabazon.com" local="3521289704" remote="12126827492" /><file name="world-cup-20103.jpg" server="scottbrabazon.com" local="3521289703" remote="12126827492" /><file name="world-cup-201030.jpg" server="scottbrabazon.com" local="3521289704" remote="12126827492" /><file name="world-cup-201031.jpg" server="scottbrabazon.com" local="3521289705" remote="12126827492" /><file name="world-cup-201032.jpg" server="scottbrabazon.com" local="3521289705" remote="12126827492" /><file name="world-cup-201033.jpg" server="scottbrabazon.com" local="3521289705" remote="12126827492" /><file name="world-cup-201034.jpg" server="scottbrabazon.com" local="3521289705" remote="12126827492" /><file name="world-cup-201035.jpg" server="scottbrabazon.com" local="3521289705" remote="12126827492" /><file name="world-cup-201036.jpg" server="scottbrabazon.com" local="3521289705" remote="12126827492" /><file name="world-cup-201037.jpg" server="scottbrabazon.com" local="3521289705" remote="12126827492" /><file name="world-cup-201038.jpg" server="scottbrabazon.com" local="3521289705" remote="12126827492" /><file name="world-cup-201039.jpg" server="scottbrabazon.com" local="3521289705" remote="12126827492" /><file name="world-cup-20104.jpg" server="scottbrabazon.com" local="3521289703" remote="12126827492" /><file name="world-cup-201040.jpg" server="scottbrabazon.com" local="3521289705" remote="12126827492" /><file name="world-cup-201041.jpg" server="scottbrabazon.com" local="3521289705" remote="12126827492" /><file name="world-cup-201042.jpg" server="scottbrabazon.com" local="3521289705" remote="12126827492" /><file name="world-cup-201043.jpg" server="scottbrabazon.com" local="3521289705" remote="12126827492" /><file name="world-cup-201044.jpg" server="scottbrabazon.com" local="3521289705" remote="12126827492" /><file name="world-cup-201045.jpg" server="scottbrabazon.com" local="3521289705" remote="12126827492" /><file name="world-cup-201046.jpg" server="scottbrabazon.com" local="3521289705" remote="12126827492" /><file name="world-cup-201047.jpg" server="scottbrabazon.com" local="3521289706" remote="12126827492" /><file name="world-cup-201048.jpg" server="scottbrabazon.com" local="3521289705" remote="12126827492" /><file name="world-cup-201049.jpg" server="scottbrabazon.com" local="3521289706" remote="12126827492" /><file name="world-cup-20105.jpg" server="scottbrabazon.com" local="3521289703" remote="12126827492" /><file name="world-cup-201050.jpg" server="scottbrabazon.com" local="3521289706" remote="12126827492" /><file name="world-cup-201051.jpg" server="scottbrabazon.com" local="3521289706" remote="12126827492" /><file name="world-cup-201052.jpg" server="scottbrabazon.com" local="3521289706" remote="12126827492" /><file name="world-cup-201053.jpg" server="scottbrabazon.com" local="3521289706" remote="12126827492" /><file name="world-cup-201054.jpg" server="scottbrabazon.com" local="3521289706" remote="12126827492" /><file name="world-cup-201055.jpg" server="scottbrabazon.com" local="3521289706" remote="12126827492" /><file name="world-cup-201056.jpg" server="scottbrabazon.com" local="3521289706" remote="12126827492" /><file name="world-cup-201057.jpg" server="scottbrabazon.com" local="3521289706" remote="12126827552" /><file name="world-cup-201058.jpg" server="scottbrabazon.com" local="3521289706" remote="12126827552" /><file name="world-cup-201059.jpg" server="scottbrabazon.com" local="3521289706" remote="12126827552" /><file name="world-cup-20106.jpg" server="scottbrabazon.com" local="3521289703" remote="12126827552" /><file name="world-cup-20107.jpg" server="scottbrabazon.com" local="3521289703" remote="12126827552" /><file name="world-cup-20108.jpg" server="scottbrabazon.com" local="3521289703" remote="12126827552" /><file name="world-cup-20109.jpg" server="scottbrabazon.com" local="3521289703" remote="12126827552" /><file name="world-cup-thumbnail.png" server="scottbrabazon.com" local="3521289838" remote="12126827552" /><file name="guitar1.jpg" server="scottbrabazon.com" local="3521289694" remote="12126827372" /><file name="guitar2.jpg" server="scottbrabazon.com" local="3521289694" remote="12126827372" /><file name="guitar3.jpg" server="scottbrabazon.com" local="3521289694" remote="12126827372" /><file name="guitar4.jpg" server="scottbrabazon.com" local="3521289694" remote="12126827372" /><file name="guitar5.jpg" server="scottbrabazon.com" local="3521289695" remote="12126827372" /><file name="guitar6.jpg" server="scottbrabazon.com" local="3521289695" remote="12126827372" /><file name="guitar8.jpg" server="scottbrabazon.com" local="3521289696" remote="12126827372" /><file name="guitar7.jpg" server="scottbrabazon.com" local="3521289696" remote="12126827372" /><file name="flourish.svg" server="scottbrabazon.com" local="3536229469" remote="12127184252" /><file name="home-icon-black.svg" server="scottbrabazon.com" local="3536232759" remote="12127184252" /><file name="home-icon-gold.svg" server="scottbrabazon.com" local="3536233430" remote="12126827372" /><file name=".DS_Store" server="scottbrabazon.com" local="3536913319" remote="12126827372" /><file name="warren-email-newsletter.jpg" server="scottbrabazon.com" local="3521289703" remote="12127184252" /><file name="wd40-email.jpg" server="scottbrabazon.com" local="3537270734" remote="12127184252" /><file name="warren-email-xmas.jpg" server="scottbrabazon.com" local="3537271071" remote="12127184252" /><file name="close.png" server="scottbrabazon.com/public_html/" local="3521289997" remote="12133218272" /><file name="loading.gif" server="scottbrabazon.com/public_html/" local="3479013910" remote="12133218272" /><file name="prev.png" server="scottbrabazon.com/public_html/" local="3521289926" remote="12133218272" /><file name="next.png" server="scottbrabazon.com/public_html/" local="3521289932" remote="12133218272" /><file name="background-wide-wallpaper-1920x1080-005.jpg" server="scottbrabazon.com/public_html/" local="3521289692" remote="12133218332" /><file name="home-icon-black.svg" server="scottbrabazon.com/public_html/" local="3536232759" remote="12133238612" /><file name="aflemail.jpg" server="scottbrabazon.com/public_html/" local="3521289690" remote="12129863912" /><file name="bikeandgo.jpg" server="scottbrabazon.com/public_html/" local="3521289693" remote="12129863912" /><file name="joneshomesemail.jpg" server="scottbrabazon.com/public_html/" local="3521289697" remote="12129863912" /><file name="warren-email-newsletter.jpg" server="scottbrabazon.com/public_html/" local="3521289703" remote="12129863912" /><file name="wd40-email.jpg" server="scottbrabazon.com/public_html/" local="3537270734" remote="12129863912" /><file name="warren-email-xmas.jpg" server="scottbrabazon.com/public_html/" local="3537271071" remote="12129863912" /><file name="flourish.svg" server="scottbrabazon.com/public_html/" local="3536229469" remote="12133238612" /><file name="linkedin.png" server="scottbrabazon.com/public_html/" local="3521289956" remote="12133238612" /><file name="home-icon-gold.svg" server="scottbrabazon.com/public_html/" local="3536233430" remote="12133238672" /><file name="world-cup-thumbnail.png" server="scottbrabazon.com/public_html/" local="3521289838" remote="12133238672" /><file name="wd40cans_thumbnail.png" server="scottbrabazon.com/public_html/" local="3521289875" remote="12133238672" /><file name="mancitystore_thumbnail.png" server="scottbrabazon.com/public_html/" local="3521289950" remote="12133238672" /><file name="guitar_thumbnail.png" server="scottbrabazon.com/public_html/" local="3521289981" remote="12133238672" /><file name="mufc2011_thumbnail.png" server="scottbrabazon.com/public_html/" local="3521289938" remote="12133238672" /><file name="argos_ss2012_thumbnail.png" server="scottbrabazon.com/public_html/" local="3521290020" remote="12133238672" /><file name="chelsea_thumbnail.png" server="scottbrabazon.com/public_html/" local="3521290003" remote="12133238672" /><file name="mcfc_thumbnail.png" server="scottbrabazon.com/public_html/" local="3521289944" remote="12133238672" /><file name="bia-thumbnail.png" server="scottbrabazon.com/public_html/" local="3543321848" remote="12133238612" /><file name="jesters-thumbnail.png" server="scottbrabazon.com/public_html/" local="3543322866" remote="12133239692" /></dwsync>